scotils/__init__.py
scotils/finance/__init__.py
scotils/finance/gambling/__init__.py
scotils/finance/gambling/arbitrage.py
scotils/singletons/__init__.py
scotils/singletons/undefined.py
scotils/strings/__init__.py
scotils/strings/utils.py
scotils-0.2.3.dist-info/licenses/LICENSE
scotils-0.2.3.dist-info/METADATA
scotils-0.2.3.dist-info/WHEEL
scotils-0.2.3.dist-info/top_level.txt
scotils-0.2.3.dist-info/RECORD
