Metadata-Version: 2.4
Name: scotils
Version: 0.2.3
Summary: Workspace for scotils utilities
Author: Scott Caratozzolo
License-Expression: MIT
Project-URL: Homepage, https://gitlab.com/caratozzoloxyz/public/scotils
Project-URL: Repository, https://gitlab.com/caratozzoloxyz/public/scotils
Project-URL: Issues, https://gitlab.com/caratozzoloxyz/public/scotils/-/issues
Requires-Python: >=3.9
License-File: LICENSE
Dynamic: license-file
